{
  "id": "476419b5-aebf-4366-a131-ae3e8dae5fc2",
  "name": "Windows - Overwrite file with SysInternals SDelete",
  "description": "Overwrites and deletes a file using SysInternals SDelete. Upon successful execution, \"Files deleted: 1\" will be displayed in\nthe powershell session along with other information about the file that was deleted.\n",
  "platforms": [
    "windows"
  ],
  "steps": [
    {
      "id": "271ae3e1-b639-4363-bb02-5a726518b7c4",
      "type": "execute-command",
      "data": {
        "command": "if (-not (Test-Path \"#{file_to_delete}\")) { New-Item \"#{file_to_delete}\" -Force }\n\u0026 \"#{sdelete_exe}\" -accepteula \"#{file_to_delete}\"\n",
        "command_type": "powershell"
      },
      "elevation_required": false
    },
    {
      "id": "fad1f0b9-a247-47ef-b0c0-102d36320d67",
      "name": "Check dependency 1/1",
      "description": "Secure delete tool from SysInternals must exist on disk at specified location (#{sdelete_exe})\n",
      "type": "execute-command",
      "data": {
        "command": "if (Test-Path \"#{sdelete_exe}\") {exit 0} else {exit 1}\n",
        "command_type": ""
      },
      "elevation_required": false
    },
    {
      "id": "36577375-8541-4261-91e0-39514bf6ea91",
      "name": "Resolve dependency 1/1",
      "description": "Secure delete tool from SysInternals must exist on disk at specified location (#{sdelete_exe})\n",
      "type": "execute-command",
      "data": {
        "command": "New-Item -Type Directory \"PathToAtomicsFolder\\..\\ExternalPayloads\\\" -ErrorAction Ignore -Force | Out-Null\nInvoke-WebRequest \"https://download.sysinternals.com/files/SDelete.zip\" -OutFile \"PathToAtomicsFolder\\..\\ExternalPayloads\\SDelete.zip\"\nExpand-Archive \"PathToAtomicsFolder\\..\\ExternalPayloads\\SDelete.zip\" \"PathToAtomicsFolder\\..\\ExternalPayloads\\Sdelete\" -Force\nRemove-Item \"PathToAtomicsFolder\\..\\ExternalPayloads\\SDelete.zip\" -Force\n",
        "command_type": ""
      },
      "elevation_required": false
    },
    {
      "id": "b2d601bf-4795-4dee-86de-7d0f88d474aa",
      "name": "Re-check dependency 1/1",
      "description": "Secure delete tool from SysInternals must exist on disk at specified location (#{sdelete_exe})\n",
      "type": "execute-command",
      "data": {
        "command": "if (Test-Path \"#{sdelete_exe}\") {exit 0} else {exit 1}\n",
        "command_type": ""
      },
      "elevation_required": false
    }
  ],
  "flows": [
    {
      "s": "fad1f0b9-a247-47ef-b0c0-102d36320d67",
      "p": "on-success",
      "o": "271ae3e1-b639-4363-bb02-5a726518b7c4"
    },
    {
      "s": "fad1f0b9-a247-47ef-b0c0-102d36320d67",
      "p": "on-failure",
      "o": "36577375-8541-4261-91e0-39514bf6ea91"
    },
    {
      "s": "36577375-8541-4261-91e0-39514bf6ea91",
      "p": "on-success",
      "o": "b2d601bf-4795-4dee-86de-7d0f88d474aa"
    },
    {
      "s": "b2d601bf-4795-4dee-86de-7d0f88d474aa",
      "p": "on-failure",
      "o": "271ae3e1-b639-4363-bb02-5a726518b7c4"
    }
  ],
  "tags": [
    "T1485",
    "atomic-red-team"
  ],
  "input_arguments": [
    {
      "name": "sdelete_exe",
      "type": "path",
      "description": "Path of sdelete executable",
      "value": "PathToAtomicsFolder\\..\\ExternalPayloads\\Sdelete\\sdelete.exe"
    },
    {
      "name": "file_to_delete",
      "type": "path",
      "description": "Path of file to delete",
      "value": "PathToAtomicsFolder\\..\\ExternalPayloads\\T1485.txt"
    }
  ]
}