{
  "id": "918f70ab-e1ef-49ff-bc57-b27021df84dd",
  "name": "Shutdown System via `halt` - FreeBSD/Linux",
  "description": "This test shuts down a FreeBSD/Linux system using `halt`.\n",
  "platforms": [
    "linux"
  ],
  "steps": [
    {
      "id": "184780f5-98e5-435c-8fa9-4527a850c286",
      "type": "execute-command",
      "data": {
        "command": "halt -p\n",
        "command_type": "sh"
      },
      "elevation_required": false
    }
  ],
  "tags": [
    "T1529",
    "atomic-red-team"
  ]
}